ltn/__init__.py
ltn/core.py
ltn/fuzzy_ops.py
LTNtorch-1.0.2.dist-info/LICENSE
LTNtorch-1.0.2.dist-info/METADATA
LTNtorch-1.0.2.dist-info/WHEEL
LTNtorch-1.0.2.dist-info/top_level.txt
LTNtorch-1.0.2.dist-info/RECORD
