Metadata-Version: 2.1
Name: LTNtorch
Version: 1.0.2
Summary: LTNtorch: PyTorch implementation of Logic Tensor Networks
Home-page: https://github.com/bmxitalia/LTNtorch
Author: Tommaso Carraro
Author-email: tommaso.carraro@studenti.unipd.it
License: MIT
Download-URL: https://github.com/bmxitalia/LTNtorch
Keywords: pytorch,machine-learning,framework,neural-symbolic-computing,fuzzy-logic
Platform: UNKNOWN
Classifier: Development Status :: 5 - Production/Stable
Classifier: Programming Language :: Python :: 3.7
Classifier: Programming Language :: Python :: 3.8
Classifier: Programming Language :: Python :: 3.9
Classifier: Topic :: Scientific/Engineering :: Artificial Intelligence
Classifier: License :: OSI Approved :: MIT License
Requires-Python: >=3.7
License-File: LICENSE
Requires-Dist: numpy
Requires-Dist: torch
